Metadata-Version: 2.1
Name: marsh
Version: 0.2.6
Summary: (Un)marshaling framework.
Home-page: https://github.com/adriansahlman/marsh
Author: Adrian Sahlman
Author-email: adrian.sahlman@gmail.com
License: MIT
Keywords: marshal unmarshal configuration
Platform: UNKNOWN
Classifier: Programming Language :: Python :: 3
Classifier: Programming Language :: Python :: 3 :: Only
Classifier: Programming Language :: Python :: 3.8
Classifier: Programming Language :: Python :: 3.9
Classifier: Programming Language :: Python :: 3.10
Classifier: Development Status :: 3 - Alpha
Classifier: Intended Audience :: Developers
Requires-Python: >=3.8
Requires-Dist: typing-extensions (>=4.2)
Requires-Dist: omegaconf (>=2.1.1)
Requires-Dist: docstring-parser (>=0.7.3)
Requires-Dist: dateparser (>=1.1.1)
